{"stats":{"minecraft:killed":{"minecraft:cave_spider":28,"minecraft:skeleton":77,"minecraft:magma_cube":7,"minecraft:iron_golem":5,"minecraft:pillager":3,"minecraft:zombie":97,"minecraft:glow_squid":2,"minecraft:breeze":5,"minecraft:enderman":5,"minecraft:witch":1,"minecraft:spider":31,"minecraft:silverfish":14,"minecraft:piglin":1,"minecraft:pig":3,"minecraft:creeper":35,"minecraft:sheep":34,"minecraft:ghast":3,"minecraft:blaze":18,"minecraft:phantom":4,"minecraft:drowned":25,"minecraft:wither_skeleton":3,"minecraft:villager":5},"minecraft:crafted":{"minecraft:smooth_stone":3,"minecraft:oak_sign":9,"minecraft:blaze_powder":2,"minecraft:oak_pressure_plate":1,"minecraft:birch_boat":3,"minecraft:chain":6,"minecraft:loom":1,"minecraft:diamond_shovel":3,"minecraft:lever":1,"minecraft:bookshelf":23,"minecraft:cooked_mutton":42,"minecraft:dark_oak_hanging_sign":6,"minecraft:mace":1,"minecraft:glass":104,"minecraft:diamond_helmet":2,"minecraft:repeater":4,"minecraft:diamond_leggings":1,"minecraft:iron_door":3,"minecraft:birch_door":3,"minecraft:golden_axe":1,"minecraft:glass_bottle":12,"minecraft:emerald":625,"minecraft:diamond_axe":4,"minecraft:smithing_table":1,"minecraft:campfire":3,"minecraft:cartography_table":1,"minecraft:bolt_armor_trim_smithing_template":4,"minecraft:stone_brick_stairs":18,"minecraft:bamboo_planks":70,"minecraft:lectern":6,"minecraft:crafter":1,"minecraft:stone_slab":12,"minecraft:compass":8,"minecraft:iron_pickaxe":3,"minecraft:iron_block":6,"minecraft:gold_ingot":42,"minecraft:composter":3,"minecraft:golden_carrot":144,"minecraft:smooth_stone_slab":6,"minecraft:iron_nugget":18,"minecraft:diamond_hoe":1,"minecraft:bone_meal":354,"minecraft:spruce_fence":3,"minecraft:dark_oak_fence":18,"minecraft:polished_diorite":4,"minecraft:ladder":108,"minecraft:spruce_slab":6,"minecraft:stone_pickaxe":2,"minecraft:diamond_boots":1,"minecraft:spruce_boat":1,"minecraft:dark_oak_planks":856,"minecraft:wheat":576,"minecraft:crossbow":1,"minecraft:enchanting_table":1,"minecraft:polished_granite":12,"minecraft:dark_oak_button":2,"minecraft:enchanted_book":16,"minecraft:golden_apple":3,"minecraft:fermented_spider_eye":1,"minecraft:oak_stairs":4,"minecraft:iron_shovel":5,"minecraft:iron_leggings":1,"minecraft:armor_stand":2,"minecraft:white_bed":5,"minecraft:oak_planks":1912,"minecraft:cobblestone_slab":6,"minecraft:barrel":7,"minecraft:dark_oak_boat":4,"minecraft:cooked_chicken":16,"minecraft:oak_hanging_sign":12,"minecraft:cobblestone_stairs":33,"minecraft:stone":41,"minecraft:bamboo_block":99,"minecraft:dark_oak_door":6,"minecraft:hopper":12,"minecraft:stone_brick_slab":18,"minecraft:bow":3,"minecraft:iron_boots":1,"minecraft:chest":35,"minecraft:flow_armor_trim_smithing_template":4,"minecraft:oak_button":4,"minecraft:copper_block":2,"minecraft:chiseled_stone_bricks":36,"minecraft:rail":16,"minecraft:oak_fence":9,"minecraft:stone_bricks":168,"minecraft:smoker":1,"minecraft:dropper":1,"minecraft:oak_slab":54,"minecraft:item_frame":1,"minecraft:cauldron":1,"minecraft:map":20,"minecraft:crafting_table":20,"minecraft:spruce_planks":140,"minecraft:baked_potato":93,"minecraft:iron_helmet":1,"minecraft:wooden_pickaxe":2,"minecraft:birch_planks":76,"minecraft:pumpkin_seeds":152,"minecraft:dispenser":1,"minecraft:apple":4,"minecraft:spruce_trapdoor":4,"minecraft:dark_oak_slab":180,"minecraft:iron_chestplate":1,"minecraft:paper":555,"minecraft:diamond_pickaxe":6,"minecraft:shield":8,"minecraft:stick":4540,"minecraft:iron_ingot":54,"minecraft:stone_sword":18,"minecraft:redstone_torch":14,"minecraft:shears":3,"minecraft:polished_andesite":80,"minecraft:oak_door":3,"minecraft:redstone":51,"minecraft:tripwire_hook":2,"minecraft:beehive":1,"minecraft:furnace":6,"minecraft:piston":11,"minecraft:dark_oak_trapdoor":4,"minecraft:dark_oak_sign":21,"minecraft:oak_trapdoor":6,"minecraft:glass_pane":176,"minecraft:flint_and_steel":1,"minecraft:scaffolding":72,"minecraft:iron_axe":4,"minecraft:iron_hoe":2,"minecraft:cobblestone_wall":6,"minecraft:chiseled_bookshelf":1,"minecraft:filled_map":3,"minecraft:honey_block":6,"minecraft:observer":16,"minecraft:sugar":1,"minecraft:red_dye":13,"minecraft:crimson_planks":44,"minecraft:diamond_sword":2,"minecraft:dark_oak_stairs":68,"minecraft:iron_sword":2,"minecraft:black_banner":6,"minecraft:bucket":8,"minecraft:stone_axe":2,"minecraft:air":0,"minecraft:bread":353,"minecraft:oak_boat":6,"minecraft:stonecutter":1,"minecraft:anvil":2,"minecraft:torch":523,"minecraft:lapis_lazuli":2,"minecraft:diamond_chestplate":3},"minecraft:used":{"minecraft:tuff_bricks":13,"minecraft:moss_block":1,"minecraft:dispenser":2,"minecraft:spruce_slab":2,"minecraft:ladder":113,"minecraft:poppy":4,"minecraft:chest":34,"minecraft:stone":249,"minecraft:quartz_stairs":1,"minecraft:rotten_flesh":6,"minecraft:soul_sand":20,"minecraft:crafter":4,"minecraft:spruce_boat":9,"minecraft:honey_block":1,"minecraft:lava_bucket":61,"minecraft:birch_sapling":7,"minecraft:polished_andesite_stairs":70,"minecraft:dark_oak_slab":147,"minecraft:dark_oak_button":8,"minecraft:stone_brick_stairs":74,"minecraft:bow":45,"minecraft:dark_oak_boat":22,"minecraft:sweet_berries":81,"minecraft:ominous_bottle":1,"minecraft:furnace":5,"minecraft:oak_sapling":6,"minecraft:cooked_cod":2,"minecraft:egg":1,"minecraft:potato":92,"minecraft:diorite":6,"minecraft:stripped_birch_log":1,"minecraft:wooden_pickaxe":47,"minecraft:composter":8,"minecraft:oak_leaves":22,"minecraft:glow_berries":17,"minecraft:golden_apple":1,"minecraft:dark_oak_trapdoor":9,"minecraft:sand":91,"minecraft:pumpkin_seeds":159,"minecraft:deepslate_iron_ore":5,"minecraft:lectern":336,"minecraft:polished_granite":7,"minecraft:oak_pressure_plate":3,"minecraft:lilac":1,"minecraft:diamond_sword":423,"minecraft:smithing_table":1,"minecraft:dark_oak_fence":12,"minecraft:birch_log":17,"minecraft:oak_boat":12,"minecraft:oak_hanging_sign":8,"minecraft:oak_trapdoor":5,"minecraft:enchanting_table":3,"minecraft:stone_sword":994,"minecraft:armor_stand":1,"minecraft:mycelium":41,"minecraft:cooked_salmon":14,"minecraft:trial_key":2,"minecraft:netherrack":331,"minecraft:torch":434,"minecraft:brewing_stand":1,"minecraft:anvil":3,"minecraft:nether_quartz_ore":1,"minecraft:stone_stairs":31,"minecraft:polished_diorite":4,"minecraft:shroomlight":1,"minecraft:iron_axe":843,"minecraft:barrel":11,"minecraft:bamboo":541,"minecraft:diamond_chestplate":1,"minecraft:basalt":47,"minecraft:cobbled_deepslate":98,"minecraft:observer":4,"minecraft:golden_axe":118,"minecraft:pointed_dripstone":3,"minecraft:wheat_seeds":67,"minecraft:water_bucket":122,"minecraft:chiseled_bookshelf":1,"minecraft:birch_planks":13,"minecraft:cartography_table":8,"minecraft:red_mushroom_block":150,"minecraft:cauldron":5,"minecraft:fletching_table":6,"minecraft:spruce_fence_gate":2,"minecraft:mossy_cobblestone":10,"minecraft:crafting_table":41,"minecraft:oak_slab":14,"minecraft:sculk_shrieker":1,"minecraft:white_bed":42,"minecraft:campfire":7,"minecraft:mushroom_stem":9,"minecraft:oak_log":48,"minecraft:diamond_pickaxe":7818,"minecraft:ominous_trial_key":4,"minecraft:diamond_shovel":3619,"minecraft:wind_charge":26,"minecraft:oak_button":6,"minecraft:iron_pickaxe":249,"minecraft:spruce_trapdoor":5,"minecraft:chiseled_stone_bricks":48,"minecraft:enchanted_book":1,"minecraft:cobblestone":438,"minecraft:potion":5,"minecraft:cooked_porkchop":3,"minecraft:porkchop":3,"minecraft:glass_pane":9,"minecraft:kelp":1,"minecraft:dandelion":9,"minecraft:sculk_vein":1,"minecraft:brown_mushroom_block":58,"minecraft:moss_carpet":4,"minecraft:iron_shovel":1011,"minecraft:oak_sign":18,"minecraft:diamond_hoe":126,"minecraft:decorated_pot":3,"minecraft:shield":226,"minecraft:iron_sword":134,"minecraft:bell":10,"minecraft:sculk_sensor":1,"minecraft:mutton":25,"minecraft:carrot":230,"minecraft:waxed_copper_grate":2,"minecraft:tuff":11,"minecraft:beehive":1,"minecraft:axolotl_bucket":4,"minecraft:obsidian":47,"minecraft:milk_bucket":1,"minecraft:glass":10,"minecraft:waxed_oxidized_copper":1,"minecraft:coal_ore":5,"minecraft:waxed_oxidized_copper_grate":11,"minecraft:stone_bricks":157,"minecraft:item_frame":2,"minecraft:deepslate_diamond_ore":41,"minecraft:repeater":8,"minecraft:magma_block":9,"minecraft:scaffolding":19,"minecraft:dark_oak_stairs":41,"minecraft:stone_pickaxe":94,"minecraft:dark_oak_sign":11,"minecraft:oak_planks":92,"minecraft:ender_pearl":1,"minecraft:sugar_cane":141,"minecraft:diamond_axe":3108,"minecraft:golden_hoe":39,"minecraft:loom":1,"minecraft:deepslate_redstone_ore":18,"minecraft:black_banner":6,"minecraft:crossbow":123,"minecraft:deepslate_lapis_ore":13,"minecraft:shears":168,"minecraft:redstone_torch":7,"minecraft:lever":3,"minecraft:dark_oak_log":154,"minecraft:mace":6,"minecraft:bread":226,"minecraft:string":1,"minecraft:deepslate":154,"minecraft:iron_door":4,"minecraft:gravel":7,"minecraft:andesite":32,"minecraft:coarse_dirt":2,"minecraft:bone_meal":299,"minecraft:golden_pickaxe":1,"minecraft:oak_fence":16,"minecraft:rose_bush":1,"minecraft:flint_and_steel":5,"minecraft:redstone":33,"minecraft:spruce_planks":3,"minecraft:sculk":1,"minecraft:deepslate_gold_ore":8,"minecraft:cooked_chicken":1,"minecraft:oak_door":3,"minecraft:dirt":2940,"minecraft:hopper":10,"minecraft:cobblestone_wall":8,"minecraft:bee_nest":2,"minecraft:spruce_fence":2,"minecraft:granite":24,"minecraft:birch_door":6,"minecraft:iron_hoe":191,"minecraft:dark_oak_planks":211,"minecraft:bookshelf":17,"minecraft:oak_stairs":3,"minecraft:golden_carrot":45,"minecraft:soul_soil":5,"minecraft:cooked_beef":1,"minecraft:red_dye":2,"minecraft:pumpkin":3,"minecraft:cooked_mutton":44,"minecraft:iron_ore":6,"minecraft:cobblestone_stairs":51,"minecraft:dark_oak_hanging_sign":1,"minecraft:glass_bottle":27,"minecraft:polished_andesite":78,"minecraft:baked_potato":138,"minecraft:brown_mushroom":1,"minecraft:cut_sandstone":1,"minecraft:birch_boat":29,"minecraft:stonecutter":41,"minecraft:cobblestone_slab":1,"minecraft:waxed_copper_block":5,"minecraft:red_mushroom":5,"minecraft:dark_oak_door":7,"minecraft:smoker":2,"minecraft:piston":11,"minecraft:apple":24,"minecraft:command_block":1,"minecraft:map":2,"minecraft:stone_axe":132,"minecraft:bucket":188,"minecraft:yellow_bed":5,"minecraft:splash_potion":1},"minecraft:dropped":{"minecraft:iron_sword":2,"minecraft:lapis_lazuli":67,"minecraft:cooked_beef":2,"minecraft:glow_ink_sac":2,"minecraft:glass_bottle":6,"minecraft:diamond":10,"minecraft:crossbow":1,"minecraft:dark_oak_slab":35,"minecraft:glow_berries":1,"minecraft:emerald":1,"minecraft:dirt":73,"minecraft:dark_oak_fence":1,"minecraft:scrape_pottery_sherd":4,"minecraft:sand":12,"minecraft:bolt_armor_trim_smithing_template":2,"minecraft:iron_pickaxe":2,"minecraft:dark_oak_planks":54,"minecraft:bone":1,"minecraft:stone_axe":5,"minecraft:sugar_cane":11,"minecraft:lever":1,"minecraft:iron_nugget":48,"minecraft:golden_chestplate":3,"minecraft:cobbled_deepslate":71,"minecraft:wheat":13,"minecraft:birch_sapling":1,"minecraft:rotten_flesh":86,"minecraft:oak_planks":7,"minecraft:glowstone_dust":32,"minecraft:waxed_copper_block":1,"minecraft:wind_charge":17,"minecraft:red_mushroom_block":62,"minecraft:jungle_stairs":2,"minecraft:leather_boots":2,"minecraft:leather_leggings":1,"minecraft:breeze_rod":3,"minecraft:enchanted_book":1,"minecraft:iron_ingot":3,"minecraft:wheat_seeds":26,"minecraft:iron_helmet":1,"minecraft:cobblestone":16,"minecraft:granite":31,"minecraft:chainmail_helmet":1,"minecraft:gray_wool":2,"minecraft:golden_carrot":69,"minecraft:ink_sac":3,"minecraft:potion":2,"minecraft:golden_hoe":1,"minecraft:paper":12,"minecraft:string":1,"minecraft:spruce_sapling":1,"minecraft:stone_sword":4,"minecraft:cocoa_beans":5,"minecraft:deepslate":35,"minecraft:clay_ball":4,"minecraft:diamond_sword":1,"minecraft:potato":3,"minecraft:spruce_boat":1,"minecraft:stone":103,"minecraft:waxed_cut_copper":1,"minecraft:spruce_planks":22,"minecraft:diamond_pickaxe":2,"minecraft:bamboo":5,"minecraft:spider_eye":3,"minecraft:stone_bricks":2,"minecraft:bow":2,"minecraft:magma_block":3,"minecraft:black_wool":3,"minecraft:guster_pottery_sherd":2,"minecraft:birch_planks":4,"minecraft:moss_block":3,"minecraft:soul_sand":25,"minecraft:brown_mushroom":1,"minecraft:oak_log":3,"minecraft:baked_potato":13,"minecraft:dark_oak_sapling":2,"minecraft:jungle_planks":6,"minecraft:flint":12,"minecraft:mace":1,"minecraft:dark_oak_log":64,"minecraft:crimson_roots":1,"minecraft:cauldron":4,"minecraft:gold_ingot":5,"minecraft:gravel":19,"minecraft:chiseled_tuff_bricks":1,"minecraft:carrot":479,"minecraft:poppy":12,"minecraft:gunpowder":2,"minecraft:beetroot_seeds":1,"minecraft:birch_door":3,"minecraft:chest":3,"minecraft:arrow":4,"minecraft:netherrack":29,"minecraft:bread":179,"minecraft:oak_slab":8,"minecraft:golden_helmet":1,"minecraft:poisonous_potato":1,"minecraft:golden_axe":2,"minecraft:polished_tuff":10,"minecraft:copper_ingot":2,"minecraft:tropical_fish":1,"minecraft:grass_block":1,"minecraft:flow_armor_trim_smithing_template":2,"minecraft:stick":258,"minecraft:diorite":78,"minecraft:torch":71,"minecraft:brown_wool":1,"minecraft:waxed_copper_bulb":1,"minecraft:bucket":1,"minecraft:dandelion":4,"minecraft:redstone":1,"minecraft:sweet_berries":18,"minecraft:kelp":28,"minecraft:tuff_bricks":22,"minecraft:flow_pottery_sherd":1,"minecraft:tuff":23,"minecraft:flint_and_steel":1,"minecraft:filled_map":6,"minecraft:shield":1,"minecraft:andesite":59,"minecraft:mossy_stone_bricks":1,"minecraft:golden_leggings":2,"minecraft:oak_sapling":14,"minecraft:golden_sword":1,"minecraft:spruce_log":20,"minecraft:stone_pickaxe":1,"minecraft:waxed_oxidized_copper_grate":3,"minecraft:brick":12},"minecraft:picked_up":{"minecraft:birch_door":6,"minecraft:iron_chestplate":1,"minecraft:anvil":1,"minecraft:lead":9,"minecraft:diamond_sword":1,"minecraft:oak_stairs":276,"minecraft:enchanted_book":5,"minecraft:brewing_stand":2,"minecraft:string":68,"minecraft:dark_oak_trapdoor":6,"minecraft:soul_soil":7,"minecraft:shroomlight":3,"minecraft:sculk_shrieker":3,"minecraft:gold_nugget":144,"minecraft:cobbled_deepslate":339,"minecraft:spruce_planks":14,"minecraft:trial_key":2,"minecraft:melon_slice":13,"minecraft:dark_oak_door":5,"minecraft:golden_helmet":2,"minecraft:composter":10,"minecraft:golden_axe":1,"minecraft:waxed_weathered_copper_bulb":4,"minecraft:waxed_copper_grate":2,"minecraft:golden_chestplate":2,"minecraft:cauldron":8,"minecraft:stone_sword":3,"minecraft:honey_bottle":1,"minecraft:tropical_fish":1,"minecraft:carved_pumpkin":2,"minecraft:bookshelf":1,"minecraft:white_terracotta":47,"minecraft:waxed_cut_copper":1,"minecraft:blaze_rod":10,"minecraft:birch_log":109,"minecraft:magma_block":18,"minecraft:cooked_beef":3,"minecraft:iron_door":5,"minecraft:water_bucket":2,"minecraft:brown_wool":1,"minecraft:dark_oak_boat":22,"minecraft:smoker":1,"minecraft:flint":33,"minecraft:stonecutter":44,"minecraft:dark_oak_sign":13,"minecraft:glowstone_dust":126,"minecraft:moss_block":24,"minecraft:honeycomb":3,"minecraft:brown_mushroom_block":122,"minecraft:ink_sac":3,"minecraft:dark_oak_log":1383,"minecraft:barrel":5,"minecraft:polished_andesite":34,"minecraft:dispenser":2,"minecraft:deepslate":1231,"minecraft:lever":4,"minecraft:deepslate_gold_ore":8,"minecraft:granite":202,"minecraft:chainmail_helmet":1,"minecraft:golden_horse_armor":1,"minecraft:bread":13,"minecraft:dark_oak_fence":1,"minecraft:ominous_trial_key":4,"minecraft:crimson_roots":2,"minecraft:diamond_pickaxe":2,"minecraft:crafting_table":31,"minecraft:coarse_dirt":2,"minecraft:bee_nest":2,"minecraft:ominous_bottle":1,"minecraft:nether_wart":6,"minecraft:clay_ball":732,"minecraft:leather_leggings":1,"minecraft:music_disc_creator":1,"minecraft:wind_charge":40,"minecraft:cornflower":2,"minecraft:flow_banner_pattern":2,"minecraft:flint_and_steel":4,"minecraft:glass_pane":9,"minecraft:cartography_table":9,"minecraft:deepslate_diamond_ore":41,"minecraft:poppy":29,"minecraft:guster_pottery_sherd":2,"minecraft:quartz_stairs":1,"minecraft:chest":24,"minecraft:birch_sapling":17,"minecraft:piston":1,"minecraft:waxed_oxidized_copper":65,"minecraft:egg":5,"minecraft:copper_ore":4,"minecraft:stone":998,"minecraft:oak_door":8,"minecraft:spruce_fence":5,"minecraft:flow_pottery_sherd":1,"minecraft:mace":1,"minecraft:carrot":467,"minecraft:redstone":262,"minecraft:mushroom_stem":55,"minecraft:decorated_pot":9,"minecraft:beetroot_seeds":1,"minecraft:shears":1,"minecraft:hay_block":98,"minecraft:flow_armor_trim_smithing_template":1,"minecraft:gold_ingot":5,"minecraft:tuff_bricks":35,"minecraft:glow_berries":17,"minecraft:mutton":57,"minecraft:white_wool":28,"minecraft:lapis_ore":4,"minecraft:stripped_oak_log":49,"minecraft:birch_leaves":19,"minecraft:red_mushroom_block":339,"minecraft:red_mushroom":52,"minecraft:crafter":3,"minecraft:filled_map":1,"minecraft:oak_log":995,"minecraft:golden_boots":2,"minecraft:sculk_vein":1,"minecraft:stone_bricks":83,"minecraft:apple":15,"minecraft:kelp":41,"minecraft:oak_fence_gate":3,"minecraft:iron_ore":8,"minecraft:glass_bottle":1,"minecraft:iron_sword":2,"minecraft:flowering_azalea":1,"minecraft:dark_oak_stairs":55,"minecraft:polished_andesite_stairs":38,"minecraft:dark_oak_slab":88,"minecraft:sculk":6,"minecraft:sweet_berries":108,"minecraft:waxed_exposed_copper_bulb":1,"minecraft:gravel":253,"minecraft:spruce_sapling":1,"minecraft:spruce_log":68,"minecraft:polished_tuff":10,"minecraft:leather_helmet":1,"minecraft:diamond_shovel":1,"minecraft:coal_ore":17,"minecraft:polished_diorite":8,"minecraft:stone_axe":1,"minecraft:diamond_axe":1,"minecraft:deepslate_redstone_ore":18,"minecraft:gray_wool":2,"minecraft:oak_button":2,"minecraft:baked_potato":14,"minecraft:stripped_dark_oak_log":7,"minecraft:hopper":1,"minecraft:ender_pearl":3,"minecraft:wheat":129,"minecraft:potion":7,"minecraft:stone_brick_stairs":44,"minecraft:raw_copper":114,"minecraft:deepslate_lapis_ore":21,"minecraft:oak_hanging_sign":5,"minecraft:iron_leggings":1,"minecraft:oak_sign":9,"minecraft:smooth_stone":9,"minecraft:bucket":1,"minecraft:rose_bush":16,"minecraft:redstone_torch":7,"minecraft:azalea":1,"minecraft:iron_pickaxe":1,"minecraft:deepslate_iron_ore":5,"minecraft:iron_boots":1,"minecraft:furnace":2,"minecraft:tipped_arrow":21,"minecraft:stick":282,"minecraft:oak_fence":76,"minecraft:torch":247,"minecraft:porkchop":3,"minecraft:pointed_dripstone":22,"minecraft:diorite":129,"minecraft:cactus":3,"minecraft:rotten_flesh":136,"minecraft:obsidian":82,"minecraft:cobblestone":1071,"minecraft:enchanting_table":2,"minecraft:lilac":1,"minecraft:magma_cream":1,"minecraft:repeater":8,"minecraft:andesite":478,"minecraft:mud_brick_stairs":1,"minecraft:potato":355,"minecraft:tuff":110,"minecraft:lapis_lazuli":450,"minecraft:dirt":3932,"minecraft:stripped_birch_log":9,"minecraft:polished_granite":17,"minecraft:leather_boots":2,"minecraft:glass":18,"minecraft:bone":207,"minecraft:bow":10,"minecraft:wheat_seeds":314,"minecraft:raw_gold":42,"minecraft:bell":13,"minecraft:bolt_armor_trim_smithing_template":2,"minecraft:mossy_stone_bricks":1,"minecraft:fletching_table":6,"minecraft:bamboo":10775,"minecraft:scrape_pottery_sherd":4,"minecraft:oak_planks":146,"minecraft:oak_pressure_plate":5,"minecraft:poisonous_potato":2,"minecraft:sand":430,"minecraft:jungle_planks":6,"minecraft:grass_block":1,"minecraft:mossy_cobblestone":26,"minecraft:spruce_fence_gate":2,"minecraft:clay":1,"minecraft:diamond":117,"minecraft:spruce_boat":10,"minecraft:waxed_oxidized_copper_grate":14,"minecraft:crossbow":1,"minecraft:breeze_rod":7,"minecraft:bone_meal":10,"minecraft:emerald":45,"minecraft:oak_sapling":70,"minecraft:netherrack":739,"minecraft:oak_leaves":122,"minecraft:cocoa_beans":5,"minecraft:azure_bluet":2,"minecraft:ladder":11,"minecraft:brown_mushroom":42,"minecraft:gold_block":5,"minecraft:brick":12,"minecraft:shield":1,"minecraft:stone_stairs":24,"minecraft:oak_trapdoor":3,"minecraft:moss_carpet":6,"minecraft:item_frame":1,"minecraft:mycelium":130,"minecraft:blackstone":31,"minecraft:oak_boat":10,"minecraft:observer":2,"minecraft:lectern":332,"minecraft:sugar_cane":760,"minecraft:spruce_trapdoor":1,"minecraft:phantom_membrane":2,"minecraft:dark_oak_sapling":77,"minecraft:raw_iron":95,"minecraft:copper_ingot":7,"minecraft:dark_oak_planks":170,"minecraft:arrow":130,"minecraft:jungle_stairs":2,"minecraft:nether_bricks":5,"minecraft:black_banner":1,"minecraft:saddle":1,"minecraft:brick_stairs":1,"minecraft:dark_oak_button":6,"minecraft:basalt":157,"minecraft:glow_ink_sac":2,"minecraft:crimson_stem":11,"minecraft:cut_sandstone":1,"minecraft:leather":1,"minecraft:waxed_copper_bulb":1,"minecraft:waxed_copper_block":6,"minecraft:gunpowder":39,"minecraft:yellow_bed":8,"minecraft:nether_wart_block":2,"minecraft:cobblestone_wall":5,"minecraft:cobblestone_stairs":27,"minecraft:cooked_mutton":2,"minecraft:podzol":1,"minecraft:iron_ingot":84,"minecraft:stripped_oak_wood":4,"minecraft:soul_sand":102,"minecraft:book":31,"minecraft:sculk_catalyst":5,"minecraft:scaffolding":10,"minecraft:oak_slab":41,"minecraft:nether_quartz_ore":5,"minecraft:emerald_block":2,"minecraft:birch_boat":27,"minecraft:pumpkin":331,"minecraft:heavy_core":1,"minecraft:quartz":338,"minecraft:dandelion":31,"minecraft:dripstone_block":7,"minecraft:blast_furnace":1,"minecraft:white_bed":38,"minecraft:spider_eye":14,"minecraft:pumpkin_seeds":29,"minecraft:sculk_sensor":11,"minecraft:campfire":4,"minecraft:honey_block":1,"minecraft:iron_helmet":2,"minecraft:terracotta":2,"minecraft:black_wool":4,"minecraft:chiseled_tuff_bricks":1,"minecraft:coal":219},"minecraft:custom":{"minecraft:interact_with_crafting_table":319,"minecraft:open_barrel":272,"minecraft:bell_ring":4,"minecraft:leave_game":49,"minecraft:time_since_death":824954,"minecraft:damage_blocked_by_shield":15446,"minecraft:play_time":1889849,"minecraft:deaths":7,"minecraft:jump":40545,"minecraft:enchant_item":14,"minecraft:interact_with_furnace":130,"minecraft:traded_with_villager":755,"minecraft:interact_with_cartography_table":3,"minecraft:sleep_in_bed":73,"minecraft:damage_dealt":65735,"minecraft:interact_with_smoker":18,"minecraft:inspect_dispenser":13,"minecraft:use_cauldron":26,"minecraft:horse_one_cm":1506265,"minecraft:interact_with_smithing_table":21,"minecraft:interact_with_anvil":14,"minecraft:inspect_hopper":5,"minecraft:sneak_time":107966,"minecraft:interact_with_blast_furnace":1,"minecraft:total_world_time":1889849,"minecraft:interact_with_stonecutter":18,"minecraft:time_since_rest":6761,"minecraft:swim_one_cm":928932,"minecraft:fly_one_cm":9073776,"minecraft:open_chest":2088,"minecraft:fall_one_cm":1060324,"minecraft:animals_bred":15,"minecraft:sprint_one_cm":4879625,"minecraft:drop":369,"minecraft:talked_to_villager":1358,"minecraft:interact_with_brewingstand":6,"minecraft:walk_on_water_one_cm":269621,"minecraft:interact_with_loom":8,"minecraft:crouch_one_cm":382118,"minecraft:mob_kills":420,"minecraft:fill_cauldron":2,"minecraft:interact_with_campfire":2,"minecraft:climb_one_cm":140588,"minecraft:walk_one_cm":4974798,"minecraft:walk_under_water_one_cm":176196,"minecraft:boat_one_cm":3977508,"minecraft:damage_taken":22330,"minecraft:damage_absorbed":40},"minecraft:mined":{"minecraft:dark_oak_planks":46,"minecraft:white_bed":38,"minecraft:obsidian":70,"minecraft:carved_pumpkin":1,"minecraft:granite":122,"minecraft:jungle_log":1,"minecraft:oak_pressure_plate":4,"minecraft:chiseled_tuff_bricks":3,"minecraft:hopper":1,"minecraft:oak_wall_sign":3,"minecraft:nether_wart":6,"minecraft:spawner":2,"minecraft:tall_seagrass":3,"minecraft:magma_block":15,"minecraft:dark_oak_trapdoor":6,"minecraft:fire":53,"minecraft:barrel":5,"minecraft:cobbled_deepslate":8,"minecraft:moss_carpet":6,"minecraft:pumpkin":331,"minecraft:deepslate_lapis_ore":49,"minecraft:fletching_table":6,"minecraft:enchanting_table":2,"minecraft:sculk_shrieker":3,"minecraft:water_cauldron":5,"minecraft:cave_vines":6,"minecraft:oak_wall_hanging_sign":4,"minecraft:dirt_path":239,"minecraft:oak_stairs":276,"minecraft:tripwire":1,"minecraft:cut_sandstone":2,"minecraft:kelp_plant":7,"minecraft:smoker":1,"minecraft:crimson_nylium":9,"minecraft:soul_fire":3,"minecraft:powder_snow":23,"minecraft:torch":24,"minecraft:blast_furnace":1,"minecraft:mud_brick_stairs":1,"minecraft:melon":2,"minecraft:polished_andesite_stairs":37,"minecraft:glass":1,"minecraft:sugar_cane":601,"minecraft:birch_sapling":3,"minecraft:white_terracotta":47,"minecraft:waxed_copper_bulb":1,"minecraft:repeater":8,"minecraft:wheat":56,"minecraft:lilac":1,"minecraft:waxed_copper_block":15,"minecraft:pumpkin_stem":2,"minecraft:birch_door":5,"minecraft:stone_brick_stairs":39,"minecraft:oak_fence_gate":3,"minecraft:red_mushroom_block":333,"minecraft:stonecutter":42,"minecraft:piston":1,"minecraft:deepslate":2170,"minecraft:suspicious_gravel":2,"minecraft:attached_pumpkin_stem":1,"minecraft:mossy_cobblestone":31,"minecraft:stripped_birch_log":9,"minecraft:dark_oak_log":836,"minecraft:crafter":3,"minecraft:nether_bricks":5,"minecraft:spruce_fence":2,"minecraft:jungle_planks":8,"minecraft:crimson_roots":1,"minecraft:redstone_wire":23,"minecraft:kelp":11,"minecraft:red_mushroom":1,"minecraft:moss_block":22,"minecraft:cartography_table":9,"minecraft:waxed_copper_grate":7,"minecraft:andesite":390,"minecraft:potatoes":78,"minecraft:vine":1,"minecraft:bamboo_sapling":2,"minecraft:bamboo":1046,"minecraft:waxed_weathered_copper_bulb":4,"minecraft:white_wool":4,"minecraft:oak_slab":32,"minecraft:glass_pane":19,"minecraft:soul_sand":61,"minecraft:observer":2,"minecraft:dandelion":15,"minecraft:short_grass":348,"minecraft:campfire":4,"minecraft:copper_ore":16,"minecraft:tall_grass":61,"minecraft:deepslate_gold_ore":27,"minecraft:diorite":65,"minecraft:coarse_dirt":2,"minecraft:cobblestone_wall":5,"minecraft:dark_oak_wall_sign":3,"minecraft:spruce_log":40,"minecraft:birch_leaves":123,"minecraft:dark_oak_sign":2,"minecraft:mycelium":228,"minecraft:dark_oak_button":4,"minecraft:gravel":218,"minecraft:dripstone_block":7,"minecraft:cobweb":3,"minecraft:oak_button":2,"minecraft:stone_bricks":60,"minecraft:fern":8,"minecraft:waxed_cut_copper_slab":1,"minecraft:spruce_planks":3,"minecraft:oak_sapling":2,"minecraft:farmland":58,"minecraft:cobblestone_stairs":24,"minecraft:sculk_vein":1,"minecraft:brewing_stand":2,"minecraft:spruce_trapdoor":1,"minecraft:cave_vines_plant":5,"minecraft:grass_block":2192,"minecraft:soul_soil":7,"minecraft:polished_diorite":4,"minecraft:composter":10,"minecraft:tuff_bricks":30,"minecraft:smooth_stone":9,"minecraft:sculk_catalyst":6,"minecraft:glowstone":33,"minecraft:iron_ore":51,"minecraft:polished_tuff":8,"minecraft:anvil":1,"minecraft:dark_oak_stairs":15,"minecraft:pointed_dripstone":9,"minecraft:azalea":1,"minecraft:waxed_cut_copper":1,"minecraft:deepslate_redstone_ore":64,"minecraft:blackstone":31,"minecraft:clay":192,"minecraft:jungle_stairs":2,"minecraft:poppy":2,"minecraft:chest":26,"minecraft:mushroom_stem":48,"minecraft:nether_quartz_ore":296,"minecraft:cobblestone":400,"minecraft:oak_planks":129,"minecraft:iron_door":3,"minecraft:wall_torch":67,"minecraft:cauldron":3,"minecraft:deepslate_copper_ore":6,"minecraft:seagrass":3,"minecraft:stone_stairs":19,"minecraft:warped_nylium":18,"minecraft:dark_oak_slab":45,"minecraft:dark_oak_door":3,"minecraft:nether_wart_block":2,"minecraft:yellow_wool":5,"minecraft:birch_log":97,"minecraft:stripped_oak_wood":4,"minecraft:oak_log":960,"minecraft:waxed_oxidized_copper":66,"minecraft:sand":373,"minecraft:dirt":938,"minecraft:dispenser":2,"minecraft:netherrack":836,"minecraft:oak_leaves":375,"minecraft:nether_gold_ore":29,"minecraft:diamond_ore":1,"minecraft:tuff":196,"minecraft:quartz_stairs":1,"minecraft:dark_oak_leaves":21,"minecraft:deepslate_diamond_ore":105,"minecraft:oak_door":7,"minecraft:lever":3,"minecraft:ladder":11,"minecraft:decorated_pot":17,"minecraft:brick_stairs":1,"minecraft:brown_mushroom_block":143,"minecraft:spruce_leaves":12,"minecraft:crimson_stem":14,"minecraft:large_fern":1,"minecraft:hay_block":98,"minecraft:oak_trapdoor":6,"minecraft:furnace":2,"minecraft:carrots":75,"minecraft:chiseled_sandstone":1,"minecraft:gold_block":5,"minecraft:bell":6,"minecraft:bookshelf":11,"minecraft:shroomlight":3,"minecraft:deepslate_iron_ore":30,"minecraft:stripped_oak_log":48,"minecraft:packed_ice":46,"minecraft:stone":1514,"minecraft:oak_hanging_sign":1,"minecraft:podzol":182,"minecraft:waxed_exposed_copper_bulb":2,"minecraft:scaffolding":10,"minecraft:stripped_dark_oak_log":7,"minecraft:basalt":160,"minecraft:polished_granite":6,"minecraft:oak_fence":81,"minecraft:crafting_table":31,"minecraft:honey_block":1,"minecraft:rose_bush":1,"minecraft:sculk_sensor":13,"minecraft:lectern":332,"minecraft:lapis_ore":12,"minecraft:sculk":56,"minecraft:cactus":1,"minecraft:waxed_oxidized_copper_grate":12,"minecraft:redstone_torch":7,"minecraft:sweet_berry_bush":8,"minecraft:black_wall_banner":1,"minecraft:ice":9,"minecraft:bee_nest":2,"minecraft:yellow_bed":9,"minecraft:coal_ore":130,"minecraft:cocoa":3,"minecraft:flower_pot":1,"minecraft:cracked_stone_bricks":2,"minecraft:terracotta":2,"minecraft:polished_andesite":10,"minecraft:mossy_stone_bricks":1},"minecraft:broken":{"minecraft:diamond_shovel":1,"minecraft:stone_sword":14,"minecraft:wooden_pickaxe":1,"minecraft:shield":4,"minecraft:iron_axe":2,"minecraft:iron_shovel":4,"minecraft:golden_leggings":1,"minecraft:golden_hoe":1,"minecraft:golden_axe":3,"minecraft:diamond_axe":1,"minecraft:leather_boots":1},"minecraft:killed_by":{"minecraft:piglin_brute":2,"minecraft:zombie":1,"minecraft:drowned":1,"minecraft:spider":1,"minecraft:skeleton":2}},"DataVersion":3953}